<?xml version='1.0' encoding='windows-1252' ?>
<!DOCTYPE ViewObject SYSTEM "jbo_03_01.dtd">
<!---->

<ViewObject
   xmlns="http://xmlns.oracle.com/bc4j"
   Name="WarehouseViewAll"
   Version="11.1.2.64.36"
   SelectList="Warehouse.WAREHOUSE_ID, 
       Warehouse.BUILDING, 
       Warehouse.COMPLEX, 
       Warehouse.SITE_ID, 
       Warehouse.LOCAL_DELIVERY_PREFIX, 
       Warehouse.LOCAL_DELIVERY_SUFFIX, 
       Warehouse.CARRIER_NAME"
   FromList="WAREHOUSE Warehouse"
   BindingStyle="OracleName"
   CustomQuery="false"
   ComponentClass="mil.stratis.model.view.loc.WarehouseViewAllImpl"
   FetchMode="FETCH_AS_NEEDED"
   PageIterMode="Partial"
   UseGlueCode="false" >
   <DesignTime>
      <Attr Name="_codeGenFlag2" Value="Coll|VarAccess" />
   </DesignTime>
   <EntityUsage
      Name="Warehouse"
      Entity="mil.stratis.model.entity.loc.Warehouse" >
   </EntityUsage>
   <ViewAttribute
      Name="WarehouseId"
      EntityAttrName="WarehouseId"
      EntityUsage="Warehouse"
      AliasName="WAREHOUSE_ID" >
   </ViewAttribute>
   <ViewAttribute
      Name="Building"
      IsNotNull="true"
      EntityAttrName="Building"
      EntityUsage="Warehouse"
      AliasName="BUILDING" >
   </ViewAttribute>
   <ViewAttribute
      Name="Complex"
      EntityAttrName="Complex"
      EntityUsage="Warehouse"
      AliasName="COMPLEX" >
   </ViewAttribute>
   <ViewAttribute
      Name="SiteId"
      IsNotNull="true"
      EntityAttrName="SiteId"
      EntityUsage="Warehouse"
      AliasName="SITE_ID" >
   </ViewAttribute>
   <ViewAttribute
      Name="LocalDeliveryPrefix"
      EntityAttrName="LocalDeliveryPrefix"
      EntityUsage="Warehouse"
      AliasName="LOCAL_DELIVERY_PREFIX" >
   </ViewAttribute>
   <ViewAttribute
      Name="LocalDeliverySuffix"
      EntityAttrName="LocalDeliverySuffix"
      EntityUsage="Warehouse"
      AliasName="LOCAL_DELIVERY_SUFFIX" >
   </ViewAttribute>
   <ViewAttribute
      Name="CarrierName"
      EntityAttrName="CarrierName"
      EntityUsage="Warehouse"
      AliasName="CARRIER_NAME" >
   </ViewAttribute>
</ViewObject>
