<?xml version='1.0' encoding='windows-1252' ?>
<!DOCTYPE ViewObject SYSTEM "jbo_03_01.dtd">

<ViewObject
   xmlns="http://xmlns.oracle.com/bc4j"
   Name="TempShippingReview"
   Version="11.1.2.64.36"
   BindingStyle="OracleName"
   CustomQuery="true"
   ComponentClass="mil.stratis.model.view.ship.TempShippingReviewImpl"
   FetchMode="FETCH_AS_NEEDED"
   PageIterMode="Partial"
   UseGlueCode="false" >
   <DesignTime>
      <Attr Name="_codeGenFlag2" Value="Coll|VarAccess" />
   </DesignTime>
   <ViewAttribute
      Name="LDCON"
      IsSelected="false"
      IsPersistent="false"
      Precision="255"
      Type="java.lang.String"
      ColumnType="VARCHAR2"
      AliasName="VIEW_ATTR"
      SQLType="VARCHAR" >
   </ViewAttribute>
   <ViewAttribute
      Name="ShippingManifestId"
      IsSelected="false"
      IsPersistent="false"
      Precision="255"
      Type="java.lang.String"
      ColumnType="VARCHAR2"
      AliasName="VIEW_ATTR"
      SQLType="VARCHAR" >
   </ViewAttribute>
   <ViewAttribute
      Name="ShippingId"
      IsPersistent="false"
      Type="java.lang.String"
      ColumnType="VARCHAR2"
      AliasName="VIEW_ATTR"
      SQLType="VARCHAR" >
   </ViewAttribute>
   <ViewAttribute
      Name="Tcn"
      IsSelected="false"
      IsPersistent="false"
      Type="java.lang.String"
      ColumnType="VARCHAR2"
      AliasName="VIEW_ATTR"
      SQLType="VARCHAR" >
      <Properties >
         <SchemaBasedProperties >
            <LABEL
               ResId="Tcn_LABEL" >
            </LABEL>
         </SchemaBasedProperties>
      </Properties>
   </ViewAttribute>
   <ViewAttribute
      Name="ShippingBarcode"
      IsSelected="false"
      IsPersistent="false"
      Type="java.lang.String"
      ColumnType="VARCHAR2"
      AliasName="VIEW_ATTR"
      SQLType="VARCHAR" >
      <Properties >
         <SchemaBasedProperties >
            <LABEL
               ResId="ShippingBarcode_LABEL" >
            </LABEL>
         </SchemaBasedProperties>
      </Properties>
   </ViewAttribute>
   <ViewAttribute
      Name="LeadTcn"
      IsSelected="false"
      IsPersistent="false"
      Type="java.lang.String"
      ColumnType="VARCHAR2"
      AliasName="VIEW_ATTR"
      SQLType="VARCHAR" >
      <Properties >
         <SchemaBasedProperties >
            <LABEL
               ResId="LeadTcn_LABEL" >
            </LABEL>
         </SchemaBasedProperties>
      </Properties>
   </ViewAttribute>
   <ViewAttribute
      Name="FloorLocation"
      IsSelected="false"
      IsPersistent="false"
      Type="java.lang.String"
      ColumnType="VARCHAR2"
      AliasName="VIEW_ATTR"
      SQLType="VARCHAR" >
      <Properties >
         <SchemaBasedProperties >
            <LABEL
               ResId="FloorLocation_LABEL" >
            </LABEL>
         </SchemaBasedProperties>
      </Properties>
   </ViewAttribute>
   <ViewAttribute
      Name="Aac"
      IsSelected="false"
      IsPersistent="false"
      Type="java.lang.String"
      ColumnType="VARCHAR2"
      AliasName="VIEW_ATTR"
      SQLType="VARCHAR" >
      <Properties >
         <SchemaBasedProperties >
            <LABEL
               ResId="Aac_LABEL" >
            </LABEL>
         </SchemaBasedProperties>
      </Properties>
   </ViewAttribute>
   <ViewAttribute
      Name="LastReviewDate"
      IsSelected="false"
      IsPersistent="false"
      Type="java.lang.String"
      ColumnType="VARCHAR2"
      AliasName="VIEW_ATTR"
      SQLType="VARCHAR" >
      <Properties >
         <SchemaBasedProperties >
            <LABEL
               ResId="LastReviewDate_LABEL" >
            </LABEL>
         </SchemaBasedProperties>
      </Properties>
   </ViewAttribute>
   <ViewAttribute
      Name="Scn"
      IsSelected="false"
      IsPersistent="false"
      Type="java.lang.String"
      ColumnType="VARCHAR2"
      AliasName="VIEW_ATTR"
      SQLType="VARCHAR" >
   </ViewAttribute>
   <ViewAttribute
      Name="ScnAac"
      IsSelected="false"
      IsPersistent="false"
      Type="java.lang.String"
      ColumnType="VARCHAR2"
      AliasName="VIEW_ATTR"
      SQLType="VARCHAR" >
   </ViewAttribute>
   <ViewAttribute
      Name="Status"
      IsSelected="false"
      IsPersistent="false"
      Type="java.lang.String"
      ColumnType="VARCHAR2"
      AliasName="VIEW_ATTR"
      SQLType="VARCHAR" >
   </ViewAttribute>
   <ViewAttribute
      Name="ExpectedShippingManifestId"
      IsSelected="false"
      IsPersistent="false"
      Type="java.lang.String"
      ColumnType="VARCHAR2"
      AliasName="VIEW_ATTR"
      SQLType="VARCHAR" >
   </ViewAttribute>
   <ViewAttribute
      Name="ExpectedFloorLocation"
      IsSelected="false"
      IsPersistent="false"
      Type="java.lang.String"
      ColumnType="VARCHAR2"
      AliasName="VIEW_ATTR"
      SQLType="VARCHAR" >
   </ViewAttribute>
   <ViewAttribute
      Name="ExpectedLeadTcn"
      IsSelected="false"
      IsPersistent="false"
      Type="java.lang.String"
      ColumnType="VARCHAR2"
      AliasName="VIEW_ATTR"
      SQLType="VARCHAR" >
   </ViewAttribute>
   <ViewAttribute
      Name="Message"
      IsSelected="false"
      IsPersistent="false"
      Type="java.lang.String"
      ColumnType="VARCHAR2"
      AliasName="VIEW_ATTR"
      SQLType="VARCHAR" >
   </ViewAttribute>
   <AttrArray Name="KeyAttributes">
      <Item Value="ShippingId" />
   </AttrArray>
   <ResourceBundle >
      <JavaResourceBundle
         MsgBundleClass="mil.stratis.model.view.ship.common.TempShippingReviewRowImplMsgBundle" >
      </JavaResourceBundle>
   </ResourceBundle>
</ViewObject>
